{
  "projects": [
    {
      "visible": true,
      "category": "Full Stack Application",
      "title": "Sustainabear",
      "description": "Sustainabear was built in a 48-hour group hackathon organized by WINFO. It is a marketplace for conscious consumptions! For every purchase made, a fraction of the profit is automatically donated to a preset charity or nonprofit of the vendor’s choice.",
      "tags": ["Swift", "JavaScript", "React", "Xcode"],
      "image": {
        "src": "../../images/Sustainabear.png",
        "alt": "Sustainabear",
        "linkTo": "https://anshaysaboo1586.wixsite.com/sustainabear"
      },
      "links": [
        {
          "type": "github",
          "url": "https://github.com/anshaysaboo/goldbears-ios"
        },
        {
          "type": "external",
          "url": "https://anshaysaboo1586.wixsite.com/sustainabear"
        }
      ]
    },
    {
      "visible": false,
      "category": "🧰 EXTENDABLE LAYOUT",
      "title": "Add more sections!",
      "description": "The starter includes predefined sections as well as a template for new, custom sections. Moreover, you can add new projects to this section without additional coding. Photo by Kelly Sikkema on Unsplash.",
      "tags": ["Custom Sections", "Easy-2-Use"],
      "image": {
        "src": "../../images/kelly-sikkema-Hl3LUdyKRic-unsplash.jpg",
        "alt": "Extendable Layout"
      },
      "links": [
        {
          "type": "github",
          "url": "https://github.com/konstantinmuenster/gatsby-starter-portfolio-minimal-theme"
        }
      ]
    }
  ],
  "button": {
    "visible": false,
    "label": "Visit on Github",
    "url": "https://github.com/konstantinmuenster/gatsby-theme-portfolio-minimal"
  }
}
